httpauthproxy.py
httpauthproxy-1.0.1.dist-info/DESCRIPTION.rst
httpauthproxy-1.0.1.dist-info/METADATA
httpauthproxy-1.0.1.dist-info/RECORD
httpauthproxy-1.0.1.dist-info/WHEEL
httpauthproxy-1.0.1.dist-info/entry_points.txt
httpauthproxy-1.0.1.dist-info/metadata.json
httpauthproxy-1.0.1.dist-info/top_level.txt
