Metadata-Version: 2.0
Name: httpauthproxy
Version: 1.0.1
Summary: Authenticate against identity providers with HTTP requests.
Home-page: https://github.com/joshbenner/httpauthproxy
Author: Josh Benner
Author-email: josh@bennerweb.com
License: MIT
Keywords: nginx,ldap,authentication
Platform: UNKNOWN
Classifier: License :: OSI Approved :: MIT License
Classifier: Programming Language :: Python
Classifier: Programming Language :: Python :: 3.5
Classifier: Programming Language :: Python :: 3.6
Classifier: Programming Language :: Python :: Implementation :: CPython
Requires-Dist: ldap3 (<3,>=2.4)
